LICENSE
README.md
setup.cfg
setup.py
nested_multipart_parser/__init__.py
nested_multipart_parser/drf.py
nested_multipart_parser/options.py
nested_multipart_parser/parser.py
nested_multipart_parser/temp_element.py
nested_multipart_parser.egg-info/PKG-INFO
nested_multipart_parser.egg-info/SOURCES.txt
nested_multipart_parser.egg-info/dependency_links.txt
nested_multipart_parser.egg-info/top_level.txt
tests/test_drf.py
tests/test_mixed_dot_separator.py
tests/test_mixed_separator.py
tests/test_parser.py
tests/test_parser_assign.py
tests/test_parser_separator.py